[
  {
    "": "Contaduría Pública",
    "TITULO OTORGADO": "Contador Publico",
    "DURACION ESTIMADA": "10 periodos academicos",
    "NUMERO DE CREDITOS": 158,
    "JORNADA": "Diurna/Nocturna",
    "MODALIDAD DE FORMACION": "Presencial/ Virtual",
    "VALOR MATRICULA": "$ 4.959.000",
    "BECA BIEN": "$ 2.085.000",
    "CONTACTO": "Rubiela Jimenez Aguirre",
    "CORREO": "dir_contaduria@umanizales.edu.co",
    "FACULTAD": "Ciencias Contables, Económicas y Administrativas",
    "TIPO": "PREGRADO"
  },
  {
    "": "Mercadeo Nacional e internacional",
    "TITULO OTORGADO": "Profesional en Mercadeo nacional e internacional.",
    "DURACION ESTIMADA": "10 periodos academicos",
    "NUMERO DE CREDITOS": 176,
    "JORNADA": "Diurna/Nocturna",
    "MODALIDAD DE FORMACION": "Presencial/ Virtual",
    "VALOR MATRICULA": "$ 5.383.000",
    "BECA BIEN": "$ 2.097.000",
    "CONTACTO": "Adriana Mejia Bermudez",
    "CORREO": "dir_mercadeo@umanizales.edu.co",
    "FACULTAD": "Ciencias Contables, Económicas y Administrativas",
    "TIPO": "PREGRADO"
  },
  {
    "": "Administración de empresas",
    "TITULO OTORGADO": "Administrador de empresas",
    "DURACION ESTIMADA": "9 periodos academicos",
    "NUMERO DE CREDITOS": 174,
    "JORNADA": "Diurna/Nocturna",
    "MODALIDAD DE FORMACION": "Presencial/ Virtual",
    "VALOR MATRICULA": "$ 4.959.000",
    "BECA BIEN": "$ 2.085.000",
    "CONTACTO": "Carmen Adriana Ramirez",
    "CORREO": "dir_administracion@umanizales.edu.co",
    "FACULTAD": "Ciencias Contables, Económicas y Administrativas",
    "TIPO": "PREGRADO"
  },
  {
    "": "Mercadeo",
    "TITULO OTORGADO": "Profesional en Mercadeo",
    "DURACION ESTIMADA": "9 periodos academicos",
    "NUMERO DE CREDITOS": 138,
    "JORNADA": "",
    "MODALIDAD DE FORMACION": "virtual",
    "VALOR MATRICULA": "$ 1.710.000",
    "BECA BIEN": "",
    "CONTACTO": "Adriana Mejia Bermudez",
    "CORREO": "dir_mercadeo@umanizales.edu.co",
    "FACULTAD": "Ciencias Contables, Económicas y Administrativas",
    "TIPO": "PREGRADO"
  },
  {
    "": "Finanzas y negocios internacionales",
    "TITULO OTORGADO": "Profesional en Finanzas y Negocios Internacionales",
    "DURACION ESTIMADA": "9 periodos academicos",
    "NUMERO DE CREDITOS": 138,
    "JORNADA": "",
    "MODALIDAD DE FORMACION": "virtual",
    "VALOR MATRICULA": "$ 1.710.000",
    "BECA BIEN": "",
    "CONTACTO": "Eliana Morales Zuluaga",
    "CORREO": "dir_economia@umanizales.edu.co",
    "FACULTAD": "Ciencias Contables, Económicas y Administrativas",
    "TIPO": "PREGRADO"
  },
  {
    "": "Economía",
    "TITULO OTORGADO": "Economista",
    "DURACION ESTIMADA": "9 periodos academicos",
    "NUMERO DE CREDITOS": 138,
    "JORNADA": "",
    "MODALIDAD DE FORMACION": "virtual",
    "VALOR MATRICULA": "$ 1.710.000",
    "BECA BIEN": "",
    "CONTACTO": "Eliana Morales Zuluaga",
    "CORREO": "dir_economia@umanizales.edu.co",
    "FACULTAD": "Ciencias Contables, Económicas y Administrativas",
    "TIPO": "PREGRADO"
  },
  {
    "": "Ingeniería de sistemas y telecomunicaciones",
    "TITULO OTORGADO": "Ingeniero (a) de Sistemas y Telecomunicaciones.",
    "DURACION ESTIMADA": "10 periodos academicos",
    "NUMERO DE CREDITOS": 170,
    "JORNADA": "Diurna/Nocturna",
    "MODALIDAD DE FORMACION": "Presencial",
    "VALOR MATRICULA": "$ 5.696.000",
    "BECA BIEN": "$ 2.107.000",
    "CONTACTO": "Jhon Alejandro Cardona Valencia",
    "CORREO": "acardona@umanizales.edu.co",
    "FACULTAD": "Ciencias e Ingeniería",
    "TIPO": "PREGRADO"
  },
  {
    "": "Psciología",
    "TITULO OTORGADO": "Psicologo",
    "DURACION ESTIMADA": "9 Periodos Academicos",
    "NUMERO DE CREDITOS": 171,
    "JORNADA": "Diurna",
    "MODALIDAD DE FORMACION": "Presencial",
    "VALOR MATRICULA": "$ 5.355.000",
    "BECA BIEN": "",
    "CONTACTO": "Alejandro Londoño Valencia",
    "CORREO": "dir_@umanizales.edu.co",
    "FACULTAD": "Ciencias Sociales y Humanas",
    "TIPO": "PREGRADO"
  },
  {
    "": "Comunicación social y periodismo",
    "TITULO OTORGADO": "Comunicador Social y Periodista",
    "DURACION ESTIMADA": "10 periodos academicos",
    "NUMERO DE CREDITOS": 174,
    "JORNADA": "Diurna",
    "MODALIDAD DE FORMACION": "Presencial",
    "VALOR MATRICULA": "$ 5.459.000",
    "BECA BIEN": "",
    "CONTACTO": "Adriana Villegas",
    "CORREO": "avillegas@umanizales.edu.co",
    "FACULTAD": "Ciencias Sociales y Humanas",
    "TIPO": "PREGRADO"
  },
  {
    "": "Derecho",
    "TITULO OTORGADO": "Abogado",
    "DURACION ESTIMADA": "10 periodos academicos",
    "NUMERO DE CREDITOS": 164,
    "JORNADA": "Diurna/Nocturna",
    "MODALIDAD DE FORMACION": "Presencial",
    "VALOR MATRICULA": "$ 5.900.000",
    "BECA BIEN": "$ 3.416.000",
    "CONTACTO": "Margarita Maria Villegas Herrera",
    "CORREO": "mmgaviriah@umanizales.edu.co",
    "FACULTAD": "Ciencias Jurídicas",
    "TIPO": "PREGRADO"
  },
  {
    "": "Medicina",
    "TITULO OTORGADO": "Médico",
    "DURACION ESTIMADA": "12 periodos academicos",
    "NUMERO DE CREDITOS": 288,
    "JORNADA": "Diurna",
    "MODALIDAD DE FORMACION": "Presencial",
    "VALOR MATRICULA": "$ 12.739.000",
    "BECA BIEN": "",
    "CONTACTO": "Jhon Jairo Botello Jaimes",
    "CORREO": "jbotello@umanizales.edu.co",
    "FACULTAD": "Ciencias de la Salud",
    "TIPO": "PREGRADO"
  }
]